linkapy-1.5.0.dist-info/METADATA
linkapy-1.5.0.dist-info/WHEEL
linkapy-1.5.0.dist-info/entry_points.txt
linkapy-1.5.0.dist-info/licenses/LICENSE
linkapy.libs/libgcc_s-98a1ef30.so.1
linkapy/CLI.py
linkapy/__init__.py
linkapy/example.py
linkapy/linkapy.pypy310-pp73-x86_64-linux-gnu.so
linkapy/logger.py
linkapy/parsing.py
linkapy-1.5.0.dist-info/RECORD
