Metadata-Version: 2.4
Name: linkapy
Version: 1.5.0
Requires-Dist: anndata>=0.11.1
Requires-Dist: click>=8.2.1
Requires-Dist: rich>=13.9.4
Requires-Dist: muon>=0.1.7
Requires-Dist: polars>=1.17.1
Requires-Dist: pyarrow>=18.1.0
Requires-Dist: scanpy>=1.10.4
Requires-Dist: tables>=3.10.1
Requires-Dist: levenshtein>=0.27.1
Requires-Dist: ruff ; extra == 'dev'
Requires-Dist: pytest ; extra == 'dev'
Requires-Dist: pytest-cov ; extra == 'dev'
Requires-Dist: sphinx ; extra == 'docs'
Requires-Dist: sphinx-rtd-theme ; extra == 'docs'
Requires-Dist: sphinx-autoapi ; extra == 'docs'
Requires-Dist: sphinx-click ; extra == 'docs'
Requires-Dist: build ; extra == 'build'
Provides-Extra: dev
Provides-Extra: docs
Provides-Extra: build
License-File: LICENSE
Summary: A common framework to analyse multi-modal single-cell data.
Author-email: Ward Deboutte <w@rddeboutte.com>
Requires-Python: >=3.10, <3.13
Project-URL: Homepage, https://github.com/WardDeb/linkapy
Project-URL: Repository, https://github.com/WardDeb/linkapy
Project-URL: Documentation, https://linkapy.readthedocs.io/en/stable/
